supermemo2/__init__.py
supermemo2/sm_two.py
tests/__init__.py
tests/test_sm_two.py
supermemo2-3.0.1.dist-info/LICENSE
supermemo2-3.0.1.dist-info/METADATA
supermemo2-3.0.1.dist-info/WHEEL
supermemo2-3.0.1.dist-info/top_level.txt
supermemo2-3.0.1.dist-info/RECORD
