Metadata-Version: 2.1
Name: supermemo2
Version: 3.0.1
Summary: Implemented the SM-2 algorithm for spaced repetition learning.
Home-page: https://github.com/alankan886/SuperMemo2
Author: Alan Kan
Author-email: 
License: MIT
Keywords: spaced-repetition SM-2 SuperMemo Python
Classifier: Development Status :: 5 - Production/Stable
Classifier: Intended Audience :: Education
Classifier: Operating System :: OS Independent
Classifier: License :: OSI Approved :: MIT License
Classifier: Programming Language :: Python
Classifier: Programming Language :: Python :: 3
License-File: LICENSE
Requires-Dist: attrs
